docs/conf.py
examples/carbon_pencilbeam.py
examples/helium_pencilbeam.py
examples/import_matrad_patient.py
examples/photon_pencilbeam.py
examples/proton_let_optimization.py
examples/proton_pencilbeam.py
pyRadPlan/__init__.py
pyRadPlan/analysis/__init__.py
pyRadPlan/analysis/_dvh.py
pyRadPlan/core/__init__.py
pyRadPlan/core/_exceptions.py
pyRadPlan/core/_grids.py
pyRadPlan/core/datamodel.py
pyRadPlan/core/np2sitk.py
pyRadPlan/core/resample.py
pyRadPlan/cst/__init__.py
pyRadPlan/cst/_cst.py
pyRadPlan/cst/_voi.py
pyRadPlan/ct/__init__.py
pyRadPlan/ct/_ct.py
pyRadPlan/ct/_hlut.py
pyRadPlan/data/machines/carbon_Generic.mat
pyRadPlan/data/machines/helium_Generic.mat
pyRadPlan/data/machines/photons_Generic.mat
pyRadPlan/data/machines/protons_Generic.mat
pyRadPlan/data/phantoms/TG119.mat
pyRadPlan/data/stf/matRad_stf.mat
pyRadPlan/data/stf/matRad_stf_onebeam.mat
pyRadPlan/data/stf/matrad_stf_onebeam.mat
pyRadPlan/dij/__init__.py
pyRadPlan/dij/_compose_beam_dijs.py
pyRadPlan/dij/_dij.py
pyRadPlan/dose/__init__.py
pyRadPlan/dose/_calc_dose.py
pyRadPlan/dose/engines/__init__.py
pyRadPlan/dose/engines/_base.py
pyRadPlan/dose/engines/_base_pencilbeam.py
pyRadPlan/dose/engines/_base_pencilbeam_particle.py
pyRadPlan/dose/engines/_factory.py
pyRadPlan/dose/engines/_hongpb.py
pyRadPlan/dose/engines/_svdpb.py
pyRadPlan/geometry/__init__.py
pyRadPlan/geometry/lps.py
pyRadPlan/io/__init__.py
pyRadPlan/io/_matlab_file_handler.py
pyRadPlan/io/_patient_loader.py
pyRadPlan/io/matfile.py
pyRadPlan/machines/__init__.py
pyRadPlan/machines/_base.py
pyRadPlan/machines/_ions.py
pyRadPlan/machines/_load.py
pyRadPlan/machines/_photons.py
pyRadPlan/machines/_validate.py
pyRadPlan/matRad/__init__.py
pyRadPlan/matRad/_engine.py
pyRadPlan/matRad/_matlab.py
pyRadPlan/matRad/_octave.py
pyRadPlan/optimization/__init__.py
pyRadPlan/optimization/_fluence_optimization.py
pyRadPlan/optimization/objectives/__init__.py
pyRadPlan/optimization/objectives/_eud.py
pyRadPlan/optimization/objectives/_factory.py
pyradplan-0.2.8.dist-info/licenses/LICENSE
pyradplan-0.2.8.dist-info/METADATA
pyradplan-0.2.8.dist-info/WHEEL
pyradplan-0.2.8.dist-info/top_level.txt
pyradplan-0.2.8.dist-info/RECORD
