Metadata-Version: 2.4
Name: pyRadPlan
Version: 0.2.8
Summary: A python interface and reimplementation to matRad
Author-email: Niklas Wahl <n.wahl@dkfz-heidelberg.de>, Goran Stanic <goran.stanic@dkfz-heidelberg.de>, Tim Ortkamp <tim.ortkamp@kit.edu>, Tobias Becher <t.becher@dkfz-heidelberg.de>, Lina Bucher <lina.bucher@dkfz-heidelberg.de>, Florian Leininger <florian.leininger@dkfz-heidelberg.de>, Antonios Kontopoulos <antonios.kontopoulos@dkfz-heidelberg.de>
Maintainer-email: Niklas Wahl <n.wahl@dkfz-heidelberg.de>, Goran Stanic <goran.stanic@dkfz-heidelberg.de>, Tim Ortkamp <tim.ortkamp@kit.edu>, Tobias Becher <t.becher@dkfz-heidelberg.de>
Project-URL: Homepage, https://git.dkfz.de
Classifier: Programming Language :: Python :: 3
Classifier: License :: OSI Approved :: BSD License
Classifier: Operating System :: OS Independent
Requires-Python: >=3.9
License-File: LICENSE
Requires-Dist: scipy>=1.13.0
Requires-Dist: numpy>=1.26.0
Requires-Dist: pymatreader>=1.0.0
Requires-Dist: h5py>=3.11.0
Requires-Dist: regex>=2024.5.15
Requires-Dist: pydicom>=2.4.4
Requires-Dist: numba>=0.60.0
Requires-Dist: matplotlib>=3.9.2
Requires-Dist: pydantic<2.11,>=2.10
Requires-Dist: numpydantic>=1.6.0
Requires-Dist: SimpleITK>=2.4.0
Requires-Dist: tqdm>=4.0.0
Requires-Dist: pint>=0.24.0
Provides-Extra: matlab
Requires-Dist: matlabengine; extra == "matlab"
Provides-Extra: octave
Requires-Dist: oct2py; extra == "octave"
Provides-Extra: gui
Requires-Dist: PyQt5; extra == "gui"
Provides-Extra: dev
Requires-Dist: pytest; extra == "dev"
Requires-Dist: coverage; extra == "dev"
Requires-Dist: pytest-cov; extra == "dev"
Requires-Dist: pre-commit; extra == "dev"
Requires-Dist: sphinx; extra == "dev"
Requires-Dist: numpydoc; extra == "dev"
Requires-Dist: pydata-sphinx-theme; extra == "dev"
Requires-Dist: sphinx-design; extra == "dev"
Requires-Dist: autodoc_pydantic; extra == "dev"
Requires-Dist: sphinx-autodoc-typehints; extra == "dev"
Dynamic: license-file
